open_dev/__init__.py
open_dev/cli.py
open_dev/constants.py
open_dev/src/__init__.py
open_dev/src/open_dev_repo.py
open_dev/src/utils.py
open_dev-0.1.8.dist-info/LICENSE
open_dev-0.1.8.dist-info/METADATA
open_dev-0.1.8.dist-info/WHEEL
open_dev-0.1.8.dist-info/entry_points.txt
open_dev-0.1.8.dist-info/RECORD
